QWeb/__init__.py
QWeb/__main__.py
QWeb/_version.py
QWeb/custom_config.py
QWeb/internal/__init__.py
QWeb/internal/actions.py
QWeb/internal/ajax.py
QWeb/internal/alert.py
QWeb/internal/blocks.py
QWeb/internal/checkbox.py
QWeb/internal/config.py
QWeb/internal/config_defaults.py
QWeb/internal/cookies.py
QWeb/internal/decorators.py
QWeb/internal/download.py
QWeb/internal/dragdrop.py
QWeb/internal/dropdown.py
QWeb/internal/element.py
QWeb/internal/exceptions.py
QWeb/internal/file.py
QWeb/internal/frame.py
QWeb/internal/frame_checker.py
QWeb/internal/icon.py
QWeb/internal/input_.py
QWeb/internal/input_handler.py
QWeb/internal/javascript.py
QWeb/internal/lists.py
QWeb/internal/meas.py
QWeb/internal/platform.py
QWeb/internal/screenshot.py
QWeb/internal/search_strategy.py
QWeb/internal/secrets.py
QWeb/internal/table.py
QWeb/internal/text.py
QWeb/internal/user.py
QWeb/internal/util.py
QWeb/internal/window.py
QWeb/internal/xhr.py
QWeb/internal/browser/__init__.py
QWeb/internal/browser/android.py
QWeb/internal/browser/bs_desktop.py
QWeb/internal/browser/bs_mobile.py
QWeb/internal/browser/chrome.py
QWeb/internal/browser/edge.py
QWeb/internal/browser/firefox.py
QWeb/internal/browser/safari.py
QWeb/internal/js/find_text_from_textnodes.js
QWeb/internal/js/get_all_dropdown_elements_shadow_dom.js
QWeb/internal/js/get_all_frames_from_shadow_dom.js
QWeb/internal/js/get_all_input_elements_from_shadow_dom.js
QWeb/internal/js/get_by_attributes.js
QWeb/internal/js/get_by_label.js
QWeb/internal/js/get_childnodes.js
QWeb/internal/js/get_clickable.js
QWeb/internal/js/get_clickable_from_shadow_dom.js
QWeb/internal/js/get_item_elements_from_shadow_dom.js
QWeb/internal/js/get_parent_list.js
QWeb/internal/js/get_recursive_walk.js
QWeb/internal/js/get_text_elements_from_shadow_dom.js
QWeb/internal/js/get_visibility.js
QWeb/internal/js/highlight_element.js
QWeb/internal/js/install_monitor.js
QWeb/internal/js/spinner_busy.js
QWeb/internal/js/toast_notification.js
QWeb/internal/js/wait_status_lite.js
qweb-3.7.3.dist-info/licenses/LICENSE
qweb-3.7.3.dist-info/METADATA
qweb-3.7.3.dist-info/WHEEL
qweb-3.7.3.dist-info/top_level.txt
qweb-3.7.3.dist-info/RECORD
