Metadata-Version: 2.4
Name: qweb
Version: 3.7.3
Summary: Keyword driven automation for the web
Author-email: "Copado Inc." <copadorobotictesting@copado.com>
License-Expression: Apache-2.0
Project-URL: Homepage, https://github.com/qentinelqi/qweb/
Keywords: test,automation,robot,framework
Classifier: Programming Language :: Python :: 3.10
Classifier: Programming Language :: Python :: 3.11
Classifier: Programming Language :: Python :: 3.12
Classifier: Programming Language :: Python :: 3.13
Classifier: Framework :: Robot Framework
Classifier: Framework :: Robot Framework :: Library
Requires-Python: <4.0,>3.7
License-File: LICENSE
Requires-Dist: setuptools>=70.0.0
Requires-Dist: pyscreeze==0.1.28
Requires-Dist: pyautogui>=0.9.53
Requires-Dist: pynput>=1.8.0
Requires-Dist: pypdf>=5.4.0
Requires-Dist: pyperclip==1.9.0
Requires-Dist: requests>=2.32.2
Requires-Dist: robotframework<8,>=5.0.1
Requires-Dist: robotframework-debuglibrary==2.5.0
Requires-Dist: selenium<5,>=4.27.0
Requires-Dist: Pillow>=11.0.0
Requires-Dist: scipy>=1.7.3
Requires-Dist: scikit-image==0.25.2
Requires-Dist: ply
Requires-Dist: numpy>=2.0.0
Requires-Dist: opencv-python==4.11.0.86
Requires-Dist: xlib; sys_platform == "linux"
Requires-Dist: pyobjc>=9.2; sys_platform == "darwin"
Requires-Dist: pyobjc-core>=9.2; sys_platform == "darwin"
Dynamic: license-file
